.DS_Store
handypy/__init__.py
handypy/_utils.py
handypy/hcv2.py
handypy/parallel.py
handypy/utils.py
handypy-0.2.2.dist-info/LICENSE
handypy-0.2.2.dist-info/METADATA
handypy-0.2.2.dist-info/WHEEL
handypy-0.2.2.dist-info/top_level.txt
handypy-0.2.2.dist-info/RECORD
