Metadata-Version: 2.1
Name: handypy
Version: 0.2.2
Summary: Handy Python scripts
Home-page: https://jiayiliu.github.io/handypy/
Author: Jiayi Liu
Author-email: jiayiliu@users.noreply.github.com
License: MIT
Platform: UNKNOWN
